scratchclientImproved/Activity.py
scratchclientImproved/Backpack.py
scratchclientImproved/CloudConnection.py
scratchclientImproved/Comment.py
scratchclientImproved/Forums.py
scratchclientImproved/Incomplete.py
scratchclientImproved/Message.py
scratchclientImproved/News.py
scratchclientImproved/Project.py
scratchclientImproved/Scraping.py
scratchclientImproved/ScratchExceptions.py
scratchclientImproved/ScratchSession.py
scratchclientImproved/Studio.py
scratchclientImproved/User.py
scratchclientImproved/UserProfile.py
scratchclientImproved/Websocket.py
scratchclientImproved/__init__.py
scratchclientImproved/__main__.py
scratchclientImproved/util.py
scratchclientImproved-1.3.dist-info/LICENSE.txt
scratchclientImproved-1.3.dist-info/METADATA
scratchclientImproved-1.3.dist-info/WHEEL
scratchclientImproved-1.3.dist-info/top_level.txt
scratchclientImproved-1.3.dist-info/RECORD
