Metadata-Version: 2.1
Name: scratchclientImproved
Version: 1.3
Summary: Improved Version Of The Scratch API Wrapper By CubeyTheCube
Home-page: https://github.com/StellarSt0rm/scratchclientImproved
Download-URL: https://github.com/StellarSt0rm/scratchclientImproved/archive/refs/tags/v1.3.tar.gz
Author: StellarSt0rm
Author-email: stellarst0rm.dev@gmail.com
License: MIT
Keywords: scratch,api
Classifier: Development Status :: 4 - Beta
Classifier: Intended Audience :: Developers
Classifier: License :: OSI Approved :: MIT License
Classifier: Operating System :: OS Independent
Classifier: Programming Language :: Python :: 3
Classifier: Programming Language :: Python :: 3.6
Classifier: Programming Language :: Python :: 3.7
License-File: LICENSE.txt
Requires-Dist: requests
Provides-Extra: fast
Requires-Dist: numpy ; extra == 'fast'
Requires-Dist: wsaccel ; extra == 'fast'
